LICENSE
MANIFEST.in
README.rst
setup.py
dtim/__init__.py
dtim/core.py
dtim/utils.py
dtim.egg-info/PKG-INFO
dtim.egg-info/SOURCES.txt
dtim.egg-info/dependency_links.txt
dtim.egg-info/top_level.txt