Metadata-Version: 1.0
Name: dtim
Version: 0.0.2.1
Summary: datetime improvement for standard datetime.datetime
Home-page: https://github.com/cuonglm/dtim
Author: Cuong Manh Le
Author-email: cuong.manhle.vn@gmail.com
License: BSD
Keywords: datetime
Platform: UNKNOWN
